pyspinel-1.0.1.data/scripts/extcap_ot.bat
pyspinel-1.0.1.data/scripts/extcap_ot.py
pyspinel-1.0.1.data/scripts/sniffer.py
pyspinel-1.0.1.data/scripts/spinel-cli.py
spinel/__init__.py
spinel/codec.py
spinel/common.py
spinel/config.py
spinel/const.py
spinel/hdlc.py
spinel/ipv6.py
spinel/pcap.py
spinel/stream.py
spinel/test_codec.py
spinel/test_hdlc.py
spinel/test_sniffer.py
spinel/test_stream.py
spinel/tests.py
spinel/tun.py
spinel/util.py
vendor/__init__.py
vendor/codec.py
vendor/const.py
vendor/vendor.py
pyspinel-1.0.1.dist-info/AUTHORS
pyspinel-1.0.1.dist-info/LICENSE
pyspinel-1.0.1.dist-info/METADATA
pyspinel-1.0.1.dist-info/WHEEL
pyspinel-1.0.1.dist-info/top_level.txt
pyspinel-1.0.1.dist-info/RECORD
