Metadata-Version: 1.1
Name: pyspinel
Version: 1.0.1
Summary: A Python interface to the OpenThread Network Co-Processor (NCP)
Home-page: https://github.com/openthread/openthread
Author: The OpenThread Authors
Author-email: openthread-users@googlegroups.com
License: BSD
Keywords: openthread thread spinel ncp
Platform: UNKNOWN
Classifier: Development Status :: 3 - Alpha
Classifier: Intended Audience :: Developers
Classifier: Operating System :: MacOS
Classifier: Operating System :: POSIX :: Linux
Classifier: License :: OSI Approved :: BSD License
Classifier: Topic :: System :: Networking
Classifier: Topic :: System :: Hardware :: Hardware Drivers
Classifier: Topic :: Software Development :: Embedded Systems
Classifier: Programming Language :: Python :: 3 :: Only
Classifier: Programming Language :: Python :: 3.6
